whitecircle_cli/__init__.py
whitecircle_cli/__main__.py
whitecircle_cli/logging_utils.py
whitecircle_cli/output.py
whitecircle_cli/api/__init__.py
whitecircle_cli/api/client.py
whitecircle_cli/cli/__init__.py
whitecircle_cli/cli/check_cmd.py
whitecircle_cli/cli/session_cmd.py
whitecircle_cli/cli/setup_cmd.py
whitecircle_cli/config/__init__.py
whitecircle_cli/config/paths.py
whitecircle_cli/config/profile.py
whitecircle_cli/models/types.py
whitecircle_cli/tests/test_cli_basic.py
whitecircle_cli/tests/test_more.py
whitecircle_cli-0.1.1.dist-info/METADATA
whitecircle_cli-0.1.1.dist-info/WHEEL
whitecircle_cli-0.1.1.dist-info/entry_points.txt
whitecircle_cli-0.1.1.dist-info/top_level.txt
whitecircle_cli-0.1.1.dist-info/RECORD
