Metadata-Version: 2.4
Name: whitecircle_cli
Version: 0.1.1
Summary: White Circle CLI - thin wrapper over White Circle API
Author-email: White Circle <hi@whitecircle.ai>
License: Apache-2.0
Project-URL: Homepage, https://whitecircle.ai
Keywords: cli,whitecircle,security,policy
Classifier: Programming Language :: Python :: 3
Classifier: Programming Language :: Python :: 3 :: Only
Classifier: Programming Language :: Python :: 3.13
Classifier: License :: OSI Approved :: Apache Software License
Classifier: Environment :: Console
Classifier: Topic :: Utilities
Requires-Python: >=3.13.7
Requires-Dist: click>=8.1
Requires-Dist: httpx>=0.27
Provides-Extra: dev
Requires-Dist: pytest>=8.0; extra == "dev"
Requires-Dist: ruff>=0.5.0; extra == "dev"
